jewei_mysql_mcp_server/__init__.py
jewei_mysql_mcp_server/app_config.py
jewei_mysql_mcp_server/core.py
jewei_mysql_mcp_server/server.py
jewei_mysql_mcp_server-0.2.5.dist-info/METADATA
jewei_mysql_mcp_server-0.2.5.dist-info/WHEEL
jewei_mysql_mcp_server-0.2.5.dist-info/entry_points.txt
jewei_mysql_mcp_server-0.2.5.dist-info/top_level.txt
jewei_mysql_mcp_server-0.2.5.dist-info/RECORD
