Metadata-Version: 2.4
Name: jewei-mysql-mcp-server
Version: 0.2.5
Summary: MySQL MCP服务器，提供SQL查询和表结构查询功能
Author-email: Jewei <jewei@jeweis.com>
Project-URL: Homepage, https://github.com/jewei/jewei-mysql-mcp-server
Project-URL: Bug Tracker, https://github.com/jeweis/jewei-mysql-mcp-server/issues
Classifier: Programming Language :: Python :: 3
Classifier: License :: OSI Approved :: MIT License
Classifier: Operating System :: OS Independent
Requires-Python: >=3.7
Requires-Dist: fastmcp>=0.1.0
Requires-Dist: sqlalchemy>=1.4.0
Requires-Dist: PyMySQL>=1.0.0
Requires-Dist: python-dotenv>=0.19.0
